README.md
setup.py
PyFretboard/__init__.py
PyFretboard/build_shape.py
PyFretboard/definitions.py
PyFretboard/draw_score.py
PyFretboard/draw_shape.py
PyFretboard/finger.py
PyFretboard/section.py
PyFretboard/shape.py
PyFretboard/song.py
PyFretboard/song2.py
PyFretboard/song_xml.py
PyFretboard.egg-info/PKG-INFO
PyFretboard.egg-info/SOURCES.txt
PyFretboard.egg-info/dependency_links.txt
PyFretboard.egg-info/requires.txt
PyFretboard.egg-info/top_level.txt