Metadata-Version: 2.1
Name: PyFretboard
Version: 0.4
Summary: PyFretboard is an API for drawing diagrams on the guitar fretboard.
Home-page: https://github.com/narcispr/PyFretboard
Author: Narcis Palomeras
License: UNKNOWN
Platform: UNKNOWN
Classifier: Programming Language :: Python :: 3
Classifier: License :: OSI Approved :: BSD License
Classifier: Operating System :: OS Independent
